rsaitehu/clustering.py
rsaitehu_clustering-0.0.1.dist-info/METADATA
rsaitehu_clustering-0.0.1.dist-info/WHEEL
rsaitehu_clustering-0.0.1.dist-info/top_level.txt
rsaitehu_clustering-0.0.1.dist-info/RECORD
