Metadata-Version: 2.1
Name: rsaitehu-clustering
Version: 0.0.1
Summary: clustering utilities
Requires-Dist: numpy >=1.22.0
Requires-Dist: pandas >=1.5.1
Requires-Dist: scikit-learn >=1.1.3
Requires-Dist: matplotlib >=3.5.3
